{
  "0e93b819cc2e8121f7281dc8e4eaaf78" : {
    "statistic" : {
      "failed" : 0,
      "broken" : 0,
      "skipped" : 0,
      "passed" : 1,
      "unknown" : 0,
      "total" : 1
    },
    "items" : [ {
      "uid" : "f8d9dbd4c932db21",
      "reportUrl" : "https://iiistvan.github.io/selenium-py-peldatar/35//#testresult/f8d9dbd4c932db21",
      "status" : "passed",
      "time" : {
        "start" : 1624654918604,
        "stop" : 1624654918604,
        "duration" : 0
      }
    } ]
  },
  "753cdf21aa3257d3e2249d83346a13e6" : {
    "statistic" : {
      "failed" : 0,
      "broken" : 0,
      "skipped" : 0,
      "passed" : 1,
      "unknown" : 0,
      "total" : 1
    },
    "items" : [ {
      "uid" : "2e07f38ebbf3f4e5",
      "reportUrl" : "https://iiistvan.github.io/selenium-py-peldatar/35//#testresult/2e07f38ebbf3f4e5",
      "status" : "passed",
      "time" : {
        "start" : 1624654918602,
        "stop" : 1624654918602,
        "duration" : 0
      }
    } ]
  },
  "77caee529814bb5616db6b28df37c87c" : {
    "statistic" : {
      "failed" : 0,
      "broken" : 0,
      "skipped" : 0,
      "passed" : 1,
      "unknown" : 0,
      "total" : 1
    },
    "items" : [ {
      "uid" : "81877f14f799cc7c",
      "reportUrl" : "https://iiistvan.github.io/selenium-py-peldatar/35//#testresult/81877f14f799cc7c",
      "status" : "passed",
      "time" : {
        "start" : 1624654918600,
        "stop" : 1624654918601,
        "duration" : 1
      }
    } ]
  },
  "0cc1fa42e1c19a0d3fd610d45c4ba65a" : {
    "statistic" : {
      "failed" : 0,
      "broken" : 0,
      "skipped" : 0,
      "passed" : 1,
      "unknown" : 0,
      "total" : 1
    },
    "items" : [ {
      "uid" : "47190afb8d11231a",
      "reportUrl" : "https://iiistvan.github.io/selenium-py-peldatar/35//#testresult/47190afb8d11231a",
      "status" : "passed",
      "time" : {
        "start" : 1624654918598,
        "stop" : 1624654918598,
        "duration" : 0
      }
    } ]
  }
}